anycode/__init__.py
anycode/client.py
anycode/generation.py
anycode/py.typed
anycode-0.2.0.dist-info/LICENSE
anycode-0.2.0.dist-info/METADATA
anycode-0.2.0.dist-info/WHEEL
anycode-0.2.0.dist-info/RECORD
