Metadata-Version: 2.1
Name: anycode
Version: 0.2.0
Summary: Constants and functions generated on-the-fly by ChatGPT.
Home-page: https://github.com/bfontaine/anycode
License: MIT
Author: Baptiste Fontaine
Author-email: b@ptistefontaine.fr
Requires-Python: >=3.9,<4.0
Classifier: License :: OSI Approved :: MIT License
Classifier: Programming Language :: Python :: 3
Classifier: Programming Language :: Python :: 3.9
Classifier: Programming Language :: Python :: 3.10
Classifier: Programming Language :: Python :: 3.11
Classifier: Programming Language :: Python :: 3.12
Requires-Dist: openai (>=1.12.0,<2.0.0)
Requires-Dist: python-dotenv (>=1.0.1,<2.0.0)
Requires-Dist: requests (>=2.31.0,<3.0.0)
